tbev/__init__.py
tbev/demo_word2vec_embeddings_zen.pkl
tbev/invalid.png
tbev/not_found.png
tbev/visualize.py
tbev-0.1.2.dist-info/METADATA
tbev-0.1.2.dist-info/WHEEL
tbev-0.1.2.dist-info/entry_points.txt
tbev-0.1.2.dist-info/top_level.txt
tbev-0.1.2.dist-info/RECORD
